airflow_package/__init__.py
airflow_package/my_file.py
airflow_package/my_otherfile.py
airflow_package/my_folder/__init__.py
airflow_package/my_folder/my_nested_file.py
airflow_package-0.0.5.dist-info/METADATA
airflow_package-0.0.5.dist-info/WHEEL
airflow_package-0.0.5.dist-info/top_level.txt
airflow_package-0.0.5.dist-info/RECORD
