Metadata-Version: 2.1
Name: airflow_package
Version: 0.0.5
Summary: Packaging Airflow
Author-email: Nitin keshav <nitinkeshav11@outlook.com>
License: E-daas
Keywords: one,two
Classifier: Programming Language :: Python :: 3
Requires-Dist: requests
Requires-Dist: numpy
Requires-Dist: importlib-metadata ; python_version < "3.10"
Provides-Extra: dev
Requires-Dist: airflow-package[release,static-code-qa,test] ; extra == 'dev'
Provides-Extra: release
Requires-Dist: build ; extra == 'release'
Requires-Dist: twine ; extra == 'release'
Provides-Extra: static-code-qa
Requires-Dist: pre-commit ; extra == 'static-code-qa'
Provides-Extra: test
Requires-Dist: pytest ; extra == 'test'
Requires-Dist: pytest-cov ; extra == 'test'
